win32interfaces/__init__.py
win32interfaces/com_api.py
win32interfaces-0.1.0.dist-info/METADATA
win32interfaces-0.1.0.dist-info/WHEEL
win32interfaces-0.1.0.dist-info/licenses/LICENSE
win32interfaces-0.1.0.dist-info/RECORD
