Metadata-Version: 2.4
Name: win32interfaces
Version: 0.1.0
Summary: A simplified, modern Python wrapper for pywin32 (win32com) interfaces.
Project-URL: Homepage, https://github.com/skeptofox/win32interfaces
Project-URL: Repository, https://github.com/skeptofox/win32interfaces
Project-URL: Bug Tracker, https://github.com/skeptofox/win32interfaces/issues
Author-email: skeptofox <skeptofox@gmail.com>
License: MIT License
License-File: LICENSE
Keywords: automation,pywin32,win32,win32com,windows
Classifier: Development Status :: 3 - Alpha
Classifier: Intended Audience :: Developers
Classifier: Intended Audience :: Science/Research
Classifier: License :: OSI Approved :: MIT License
Classifier: Operating System :: OS Independent
Classifier: Programming Language :: Python :: 3
Classifier: Programming Language :: Python :: 3.8
Classifier: Programming Language :: Python :: 3.9
Classifier: Programming Language :: Python :: 3.10
Classifier: Programming Language :: Python :: 3.11
Classifier: Programming Language :: Python :: 3.12
Classifier: Topic :: Software Development :: Libraries :: Python Modules
Requires-Python: >=3.8
Requires-Dist: packaging
Requires-Dist: pywin32
